xml2arr/__init__.py
xml2arr/extractor.py
xml2arr-0.1.4.dist-info/LICENSE
xml2arr-0.1.4.dist-info/METADATA
xml2arr-0.1.4.dist-info/WHEEL
xml2arr-0.1.4.dist-info/top_level.txt
xml2arr-0.1.4.dist-info/RECORD
