Metadata-Version: 2.2
Name: xml2arr
Version: 0.1.4
Summary: Extract bounding boxes from XML format to list
Author: Blazej Turczynowicz
Author-email: blazejturczynowicz@gmail.com
Keywords: bounding box,xml,xml2arr
License-File: LICENSE
Dynamic: author
Dynamic: author-email
Dynamic: description
Dynamic: description-content-type
Dynamic: keywords
Dynamic: summary
